simple_python_tools/simple_json.py
simple_python_tools/simple_logger.py
simple_python_tools/simple_os.py
simple_python_tools/simple_requests.py
simple_python_tools/simple_spider.py
simple_python_tools-0.1.8.dist-info/METADATA
simple_python_tools-0.1.8.dist-info/WHEEL
simple_python_tools-0.1.8.dist-info/RECORD
