Metadata-Version: 2.3
Name: simple-python-tools
Version: 0.1.8
Summary: 
Author: Bamboo_King
Author-email: Bamboo_King@yeah.net
Requires-Python: >=3.13
Classifier: Programming Language :: Python :: 3
Classifier: Programming Language :: Python :: 3.13
Requires-Dist: bs4
Requires-Dist: requests
